yk/__init__.py
yk/comparison.py
yk/main.py
yk/yk.py
yk-0.0.2.dist-info/LICENSE
yk-0.0.2.dist-info/METADATA
yk-0.0.2.dist-info/WHEEL
yk-0.0.2.dist-info/entry_points.txt
yk-0.0.2.dist-info/top_level.txt
yk-0.0.2.dist-info/RECORD
