Metadata-Version: 2.1
Name: yk
Version: 0.0.2
Summary: A small example package
Home-page: https://github.com/pypa/sampleproject
Author: yiane
Author-email: yiane@qq.com
License: UNKNOWN
Platform: UNKNOWN
Classifier: Programming Language :: Python :: 3
Classifier: License :: OSI Approved :: MIT License
Classifier: Operating System :: OS Independent
Requires-Python: >=3.6
Requires-Dist: requests (==2.23.0)
Requires-Dist: pandas (==1.1.2)
